eezz/__init__.py
eezz/database.py
eezz/document.py
eezz/filesrv.py
eezz/http_agent.py
eezz/server.py
eezz/service.py
eezz/table.py
eezz/tabletree.py
eezz/websocket.py
eezz/eezz.egg-info/PKG-INFO
eezz/eezz.egg-info/SOURCES.txt
eezz/eezz.egg-info/dependency_links.txt
eezz/eezz.egg-info/requires.txt
eezz/eezz.egg-info/top_level.txt
eezz/webroot/index.html
eezz/webroot/navbar.png
eezz/webroot/simple-tree.html
eezz/webroot/testws.html
eezz/webroot/webcam.html
eezz/webroot/applications/examples/__init__.py
eezz/webroot/applications/examples/directory.py
eezz/webroot/applications/examples/webcam.py
eezz/webroot/css/eezz.css
eezz/webroot/resources/eezz.lark
eezz/webroot/resources/template.html
eezz/webroot/resources/template.pot
eezz/webroot/resources/websocket.js
eezz-1.0.0.dist-info/METADATA
eezz-1.0.0.dist-info/WHEEL
eezz-1.0.0.dist-info/licenses/LICENCE
eezz-1.0.0.dist-info/RECORD
