Metadata-Version: 2.4
Name: eezz
Version: 1.0.0
Summary: HTML User Interface for Python
Project-URL: Homepage, https://eezz.biz
Project-URL: Repository, https://github.com/albert-zero/eezz_next
Project-URL: Introduction, https://eezz.biz/eezz.pdf
Author-email: Albert Zedlitz <albert.zedlitz@eezz.biz>
License-File: LICENCE
Keywords: HTML,User Interface
Classifier: Operating System :: OS Independent
Classifier: Programming Language :: Python :: 3
Requires-Python: >=3.11
Requires-Dist: beautifulsoup4
Requires-Dist: lark>=1.2.1
Requires-Dist: loguru
Requires-Dist: pycryptodome
